pyosu/__init__.py
pyosu-1.1.dist-info/METADATA
pyosu-1.1.dist-info/WHEEL
pyosu-1.1.dist-info/top_level.txt
pyosu-1.1.dist-info/RECORD
